pyXMIP/__init__.py
pyXMIP/_script_commands.py
pyXMIP/cross_reference.py
pyXMIP/schema.py
pyXMIP/bin/config.yaml
pyXMIP/bin/objects.yaml
pyXMIP/bin/scripts.yaml
pyXMIP/bin/builtin_schema/reduction/_placeholder
pyXMIP/bin/builtin_schema/source_table/NED.yaml
pyXMIP/bin/builtin_schema/source_table/SIMBAD.yaml
pyXMIP/bin/psn_maps/NED.poisson.fits
pyXMIP/bin/txt/asciilogo.txt
pyXMIP/stats/__init__.py
pyXMIP/stats/gaussian_process.py
pyXMIP/stats/map_regression.py
pyXMIP/stats/utilities.py
pyXMIP/structures/__init__.py
pyXMIP/structures/databases.py
pyXMIP/structures/map.py
pyXMIP/structures/reduction.py
pyXMIP/structures/table.py
pyXMIP/tests/__init__.py
pyXMIP/tests/conftest.py
pyXMIP/tests/test_catalogs.py
pyXMIP/tests/test_databases.py
pyXMIP/tests/utils.py
pyXMIP/utilities/__init__.py
pyXMIP/utilities/core.py
pyXMIP/utilities/geo.py
pyXMIP/utilities/logging.py
pyXMIP/utilities/optimize.py
pyXMIP/utilities/plot.py
pyXMIP/utilities/sql.py
pyXMIP/utilities/text.py
pyXMIP/utilities/types.py
pyxmip-1.0.3.data/scripts/pyxmip
pyxmip-1.0.3.dist-info/LICENSE
pyxmip-1.0.3.dist-info/METADATA
pyxmip-1.0.3.dist-info/WHEEL
pyxmip-1.0.3.dist-info/top_level.txt
pyxmip-1.0.3.dist-info/RECORD
