Metadata-Version: 2.1
Name: pyxmip
Version: 1.0.3
Summary: Cross-matching and cross-identification toolkit for astronomical surveys.
Author-email: "Eliza C. Diggins" <eliza.diggins@utah.edu>
License: MIT License
Project-URL: Homepage, https://github.com/eliza-diggins/pyXMIP
Keywords: astronomy,cross-matching,cross-identification,survey,statistics
Classifier: License :: OSI Approved :: MIT License
Classifier: Programming Language :: Python
Classifier: Programming Language :: Python :: 3
Requires-Python: >=3.9
License-File: LICENSE
Requires-Dist: scikit-learn
Requires-Dist: pandas
Requires-Dist: numpy
Requires-Dist: astropy
Requires-Dist: tqdm
Requires-Dist: SQLAlchemy
Requires-Dist: astroquery
Requires-Dist: healpy
Requires-Dist: pydantic
Requires-Dist: ruamel.yaml
Requires-Dist: matplotlib
Requires-Dist: typing-extensions
